ai_helpers/__init__.py
ai_helpers/ai_core.py
ann_ai_utils-0.0.3.dist-info/METADATA
ann_ai_utils-0.0.3.dist-info/WHEEL
ann_ai_utils-0.0.3.dist-info/top_level.txt
ann_ai_utils-0.0.3.dist-info/RECORD
