Metadata-Version: 2.4
Name: ann-ai-utils
Version: 0.0.3
Summary: AI helper utilities
Author: Ann Jo Mathew
Requires-Python: >=3.7
Requires-Dist: google-genai>=1.0.0
Requires-Dist: python-dotenv>=0.19.0
Requires-Dist: requests>=2.25.0
